[{"date":"Sun, 08 Mar 2015 20:27:00 GMT","sloc":149,"lloc":101,"functions":15,"deliveredBugs":1.2750853775850366,"maintainability":70.0617086812775,"lintErrors":[],"difficulty":46.188235294117646},{"date":"Mon, 09 Mar 2015 21:31:19 GMT","sloc":149,"lloc":101,"functions":15,"deliveredBugs":1.2750853775850366,"maintainability":70.0617086812775,"lintErrors":[],"difficulty":46.188235294117646},{"date":"Tue, 10 Mar 2015 08:06:09 GMT","sloc":114,"lloc":77,"functions":10,"deliveredBugs":0.9916650782848816,"maintainability":68.35773583921961,"lintErrors":[],"difficulty":33.932098765432094},{"date":"Wed, 11 Mar 2015 22:24:01 GMT","sloc":200,"lloc":78,"functions":10,"deliveredBugs":0.9961320380969757,"maintainability":68.35773583921961,"lintErrors":[],"difficulty":34.07407407407407},{"date":"Fri, 13 Mar 2015 15:51:04 GMT","sloc":200,"lloc":78,"functions":10,"deliveredBugs":0.9961320380969757,"maintainability":68.35773583921961,"lintErrors":[],"difficulty":34.07407407407407},{"date":"Sat, 14 Mar 2015 07:48:31 GMT","sloc":200,"lloc":78,"functions":10,"deliveredBugs":0.9961320380969757,"maintainability":68.35773583921961,"lintErrors":[],"difficulty":34.07407407407407},{"date":"Sat, 14 Mar 2015 08:18:24 GMT","sloc":200,"lloc":78,"functions":10,"deliveredBugs":0.9961320380969757,"maintainability":68.35773583921961,"lintErrors":[],"difficulty":34.07407407407407},{"date":"Thu, 26 Mar 2015 15:12:31 GMT","sloc":200,"lloc":78,"functions":10,"deliveredBugs":0.9961320380969757,"maintainability":68.35773583921961,"lintErrors":[],"difficulty":34.07407407407407},{"date":"Thu, 26 Mar 2015 15:38:30 GMT","sloc":200,"lloc":78,"functions":10,"deliveredBugs":0.9961320380969757,"maintainability":68.35773583921961,"lintErrors":[],"difficulty":34.07407407407407},{"date":"Sun, 12 Apr 2015 07:15:48 GMT","sloc":197,"lloc":76,"functions":10,"deliveredBugs":0.9827311586606934,"maintainability":68.34060535350187,"lintErrors":[],"difficulty":33.64814814814815},{"date":"Sun, 12 Apr 2015 08:10:22 GMT","sloc":197,"lloc":76,"functions":10,"deliveredBugs":0.9827311586606934,"maintainability":68.34060535350187,"lintErrors":[],"difficulty":33.64814814814815},{"date":"Fri, 26 Jun 2015 12:57:57 GMT","sloc":194,"lloc":76,"functions":10,"deliveredBugs":0.9871981184727876,"maintainability":68.33798612909183,"lintErrors":2,"difficulty":33.932098765432094},{"date":"Fri, 26 Jun 2015 13:09:05 GMT","sloc":194,"lloc":76,"functions":10,"deliveredBugs":0.9871981184727876,"maintainability":68.33798612909183,"lintErrors":2,"difficulty":33.932098765432094},{"date":"Tue, 14 Jul 2015 20:26:08 GMT","sloc":195,"lloc":76,"functions":10,"deliveredBugs":1.0093749094891404,"maintainability":68.0969698123697,"lintErrors":3,"difficulty":36},{"date":"Tue, 14 Jul 2015 20:58:04 GMT","sloc":195,"lloc":76,"functions":10,"deliveredBugs":1.0093749094891404,"maintainability":68.0969698123697,"lintErrors":3,"difficulty":36},{"date":"Tue, 21 Jul 2015 06:38:58 GMT","sloc":195,"lloc":76,"functions":10,"deliveredBugs":1.0093749094891404,"maintainability":68.0969698123697,"lintErrors":3,"difficulty":36},{"date":"Tue, 21 Jul 2015 14:20:47 GMT","sloc":196,"lloc":77,"functions":10,"deliveredBugs":1.0205653186852506,"maintainability":68.0969698123697,"lintErrors":3,"difficulty":36.44444444444444},{"date":"Wed, 22 Jul 2015 20:47:28 GMT","sloc":196,"lloc":77,"functions":10,"deliveredBugs":1.0205653186852506,"maintainability":68.0969698123697,"lintErrors":3,"difficulty":36.44444444444444},{"date":"Wed, 22 Jul 2015 20:58:52 GMT","sloc":196,"lloc":77,"functions":10,"deliveredBugs":1.0205653186852506,"maintainability":68.0969698123697,"lintErrors":3,"difficulty":36.44444444444444},{"date":"Wed, 22 Jul 2015 21:06:19 GMT","sloc":194,"lloc":76,"functions":10,"deliveredBugs":0.992149191006359,"maintainability":68.09929590843656,"lintErrors":1,"difficulty":33.84615384615385},{"date":"Wed, 22 Jul 2015 21:15:53 GMT","sloc":194,"lloc":76,"functions":10,"deliveredBugs":0.992149191006359,"maintainability":68.09929590843656,"lintErrors":1,"difficulty":33.84615384615385},{"date":"Thu, 23 Jul 2015 10:28:39 GMT","sloc":194,"lloc":76,"functions":10,"deliveredBugs":0.992149191006359,"maintainability":68.09929590843656,"lintErrors":1,"difficulty":33.84615384615385},{"date":"Thu, 23 Jul 2015 10:32:40 GMT","sloc":194,"lloc":76,"functions":10,"deliveredBugs":0.992149191006359,"maintainability":68.09929590843656,"lintErrors":1,"difficulty":33.84615384615385},{"date":"Sat, 25 Jul 2015 11:55:07 GMT","sloc":194,"lloc":76,"functions":10,"deliveredBugs":0.992149191006359,"maintainability":68.09929590843656,"lintErrors":1,"difficulty":33.84615384615385},{"date":"Thu, 06 Aug 2015 08:55:25 GMT","sloc":194,"lloc":76,"functions":10,"deliveredBugs":0.992149191006359,"maintainability":68.09929590843656,"lintErrors":1,"difficulty":33.84615384615385},{"date":"Thu, 06 Aug 2015 11:04:51 GMT","sloc":194,"lloc":76,"functions":10,"deliveredBugs":0.992149191006359,"maintainability":68.09929590843656,"lintErrors":1,"difficulty":33.84615384615385},{"date":"Fri, 11 Sep 2015 19:10:14 GMT","sloc":194,"lloc":76,"functions":10,"deliveredBugs":0.992149191006359,"maintainability":68.09929590843656,"lintErrors":1,"difficulty":33.84615384615385}]