[{"date":"Sun, 08 Mar 2015 20:27:00 GMT","sloc":40,"lloc":22,"functions":4,"deliveredBugs":0.2500537615501896,"maintainability":74.82143402002389,"lintErrors":[],"difficulty":24.34782608695652},{"date":"Mon, 09 Mar 2015 21:31:19 GMT","sloc":40,"lloc":22,"functions":4,"deliveredBugs":0.2500537615501896,"maintainability":74.82143402002389,"lintErrors":[],"difficulty":24.34782608695652},{"date":"Tue, 10 Mar 2015 08:06:08 GMT","sloc":40,"lloc":22,"functions":4,"deliveredBugs":0.2500537615501896,"maintainability":74.82143402002389,"lintErrors":[],"difficulty":24.34782608695652},{"date":"Wed, 11 Mar 2015 22:24:01 GMT","sloc":72,"lloc":22,"functions":4,"deliveredBugs":0.2500537615501896,"maintainability":74.82143402002389,"lintErrors":[],"difficulty":24.34782608695652},{"date":"Fri, 13 Mar 2015 15:51:04 GMT","sloc":72,"lloc":22,"functions":4,"deliveredBugs":0.2500537615501896,"maintainability":74.82143402002389,"lintErrors":[],"difficulty":24.34782608695652},{"date":"Sat, 14 Mar 2015 07:48:30 GMT","sloc":72,"lloc":22,"functions":4,"deliveredBugs":0.2500537615501896,"maintainability":74.82143402002389,"lintErrors":[],"difficulty":24.34782608695652},{"date":"Sat, 14 Mar 2015 08:18:23 GMT","sloc":72,"lloc":22,"functions":4,"deliveredBugs":0.2500537615501896,"maintainability":74.82143402002389,"lintErrors":[],"difficulty":24.34782608695652},{"date":"Thu, 26 Mar 2015 15:12:30 GMT","sloc":72,"lloc":22,"functions":4,"deliveredBugs":0.2500537615501896,"maintainability":74.82143402002389,"lintErrors":[],"difficulty":24.34782608695652},{"date":"Thu, 26 Mar 2015 15:38:30 GMT","sloc":72,"lloc":22,"functions":4,"deliveredBugs":0.2500537615501896,"maintainability":74.82143402002389,"lintErrors":[],"difficulty":24.34782608695652},{"date":"Sun, 12 Apr 2015 07:15:48 GMT","sloc":72,"lloc":22,"functions":4,"deliveredBugs":0.2553991389875878,"maintainability":74.77898142661837,"lintErrors":[],"difficulty":23.625},{"date":"Sun, 12 Apr 2015 08:10:21 GMT","sloc":72,"lloc":22,"functions":4,"deliveredBugs":0.2553991389875878,"maintainability":74.77898142661837,"lintErrors":[],"difficulty":23.625},{"date":"Fri, 26 Jun 2015 12:57:56 GMT","sloc":69,"lloc":22,"functions":4,"deliveredBugs":0.2588977573298835,"maintainability":74.65539496137679,"lintErrors":2,"difficulty":24.208333333333336},{"date":"Fri, 26 Jun 2015 13:09:05 GMT","sloc":69,"lloc":22,"functions":4,"deliveredBugs":0.2588977573298835,"maintainability":74.65539496137679,"lintErrors":2,"difficulty":24.208333333333336},{"date":"Tue, 14 Jul 2015 20:26:07 GMT","sloc":69,"lloc":22,"functions":4,"deliveredBugs":0.26064706650103137,"maintainability":74.64754762427802,"lintErrors":3,"difficulty":24.208333333333336},{"date":"Tue, 14 Jul 2015 20:58:04 GMT","sloc":69,"lloc":22,"functions":4,"deliveredBugs":0.26064706650103137,"maintainability":74.64754762427802,"lintErrors":3,"difficulty":24.208333333333336},{"date":"Tue, 21 Jul 2015 06:38:58 GMT","sloc":69,"lloc":22,"functions":4,"deliveredBugs":0.26064706650103137,"maintainability":74.64754762427802,"lintErrors":3,"difficulty":24.208333333333336},{"date":"Tue, 21 Jul 2015 14:20:47 GMT","sloc":69,"lloc":22,"functions":4,"deliveredBugs":0.26064706650103137,"maintainability":74.64754762427802,"lintErrors":3,"difficulty":24.208333333333336},{"date":"Wed, 22 Jul 2015 20:47:27 GMT","sloc":69,"lloc":22,"functions":4,"deliveredBugs":0.26064706650103137,"maintainability":74.64754762427802,"lintErrors":3,"difficulty":24.208333333333336},{"date":"Wed, 22 Jul 2015 20:58:51 GMT","sloc":69,"lloc":22,"functions":4,"deliveredBugs":0.26064706650103137,"maintainability":74.64754762427802,"lintErrors":3,"difficulty":24.208333333333336},{"date":"Wed, 22 Jul 2015 21:06:19 GMT","sloc":67,"lloc":21,"functions":4,"deliveredBugs":0.24107630179641343,"maintainability":74.77063492395689,"lintErrors":1,"difficulty":22.75},{"date":"Wed, 22 Jul 2015 21:15:53 GMT","sloc":67,"lloc":21,"functions":4,"deliveredBugs":0.24107630179641343,"maintainability":74.77063492395689,"lintErrors":1,"difficulty":22.75}]